serial_mcp/__init__.py
serial_mcp/__main__.py
serial_mcp/port_manager.py
serial_mcp/server.py
serial_mcp/tools.py
serial_mcp-0.3.0.dist-info/METADATA
serial_mcp-0.3.0.dist-info/WHEEL
serial_mcp-0.3.0.dist-info/entry_points.txt
serial_mcp-0.3.0.dist-info/RECORD
