Metadata-Version: 2.4
Name: serial-mcp
Version: 0.3.0
Summary: MCP server for serial port management
Project-URL: Homepage, https://github.com/davidalo/serial-mcp
Project-URL: Repository, https://github.com/davidalo/serial-mcp
Project-URL: Issues, https://github.com/davidalo/serial-mcp/issues
Requires-Python: >=3.10
Requires-Dist: mcp[cli]>=1.2.0
Requires-Dist: pydantic>=2.0
Requires-Dist: pyserial-asyncio>=0.6
Requires-Dist: pyserial>=3.5
